spotr/__init__.py
spotr/__main__.py
spotr/ami.py
spotr/availability_zone.py
spotr/client.py
spotr/config.py
spotr/destroy.py
spotr/dns.py
spotr/instance.py
spotr/key.py
spotr/launch.py
spotr/list.py
spotr/pricing.py
spotr/snapshot.py
spotr/spin_cursor.py
spotr/spot_instance.py
spotr/spotr.py
spotr/version.py
spotr-0.0.16.dist-info/METADATA
spotr-0.0.16.dist-info/WHEEL
spotr-0.0.16.dist-info/entry_points.txt
spotr-0.0.16.dist-info/top_level.txt
spotr-0.0.16.dist-info/RECORD
